Data/DataSaving.py
Data/ExcelTools.py
Data/PandasTools.py
Data/SpreadsheetDAOs.py
Data/StatisticsBase.py
Data/__init__.py
Email/EmailerBase.py
Email/__init__.py
FileSystem/CsvTools.py
FileSystem/FileSystemTools.py
FileSystem/__init__.py
FileSystem/sphinxapi.py
Logging/LoggingTools.py
Logging/__init__.py
Notebook/LatexTools.py
Notebook/__init__.py
Plotting/Decorators.py
Plotting/UtilityFunctions.py
Plotting/__init__.py
Text/NGramTools.py
Text/TextProcessingTools.py
Text/__init__.py
Utilities/Decorators.py
Utilities/OptimizationTools.py
Utilities/__init__.py
executables/__init__.py
executables/make_mirror_test_folder_structure.py
AdamTools-0.0.4.dist-info/METADATA
AdamTools-0.0.4.dist-info/WHEEL
AdamTools-0.0.4.dist-info/top_level.txt
AdamTools-0.0.4.dist-info/RECORD
